<annotation>
	<folder>wetransfer-6ed465</folder>
	<filename>IMG_8252.JPG</filename>
	<path>C:\Users\Guille\Documents\GitHub\images\Fulvia\wetransfer-6ed465\IMG_8252.JPG</path>
	<source>
		<database>Unknown</database>
	</source>
	<size>
		<width>3264</width>
		<height>2448</height>
		<depth>3</depth>
	</size>
	<segmented>0</segmented>
	<object>
		<name>negra</name>
		<pose>Unspecified</pose>
		<truncated>0</truncated>
		<difficult>0</difficult>
		<bndbox>
			<xmin>1413</xmin>
			<ymin>942</ymin>
			<xmax>1932</xmax>
			<ymax>1357</ymax>
		</bndbox>
	</object>
	<object>
		<name>negra</name>
		<pose>Unspecified</pose>
		<truncated>0</truncated>
		<difficult>0</difficult>
		<bndbox>
			<xmin>2039</xmin>
			<ymin>435</ymin>
			<xmax>2484</xmax>
			<ymax>753</ymax>
		</bndbox>
	</object>
	<object>
		<name>negra</name>
		<pose>Unspecified</pose>
		<truncated>0</truncated>
		<difficult>0</difficult>
		<bndbox>
			<xmin>2580</xmin>
			<ymin>823</ymin>
			<xmax>2884</xmax>
			<ymax>1186</ymax>
		</bndbox>
	</object>
	<object>
		<name>negra</name>
		<pose>Unspecified</pose>
		<truncated>0</truncated>
		<difficult>0</difficult>
		<bndbox>
			<xmin>2865</xmin>
			<ymin>1075</ymin>
			<xmax>3206</xmax>
			<ymax>1453</ymax>
		</bndbox>
	</object>
	<object>
		<name>negra</name>
		<pose>Unspecified</pose>
		<truncated>0</truncated>
		<difficult>0</difficult>
		<bndbox>
			<xmin>2702</xmin>
			<ymin>1675</ymin>
			<xmax>3028</xmax>
			<ymax>1975</ymax>
		</bndbox>
	</object>
	<object>
		<name>negra</name>
		<pose>Unspecified</pose>
		<truncated>0</truncated>
		<difficult>0</difficult>
		<bndbox>
			<xmin>961</xmin>
			<ymin>1668</ymin>
			<xmax>1758</xmax>
			<ymax>2260</ymax>
		</bndbox>
	</object>
	<object>
		<name>negra</name>
		<pose>Unspecified</pose>
		<truncated>0</truncated>
		<difficult>0</difficult>
		<bndbox>
			<xmin>643</xmin>
			<ymin>638</ymin>
			<xmax>1184</xmax>
			<ymax>1146</ymax>
		</bndbox>
	</object>
	<object>
		<name>negra</name>
		<pose>Unspecified</pose>
		<truncated>0</truncated>
		<difficult>0</difficult>
		<bndbox>
			<xmin>895</xmin>
			<ymin>398</ymin>
			<xmax>1143</xmax>
			<ymax>598</ymax>
		</bndbox>
	</object>
	<object>
		<name>negra</name>
		<pose>Unspecified</pose>
		<truncated>1</truncated>
		<difficult>0</difficult>
		<bndbox>
			<xmin>1110</xmin>
			<ymin>1</ymin>
			<xmax>1836</xmax>
			<ymax>312</ymax>
		</bndbox>
	</object>
	<object>
		<name>negra</name>
		<pose>Unspecified</pose>
		<truncated>0</truncated>
		<difficult>0</difficult>
		<bndbox>
			<xmin>1832</xmin>
			<ymin>75</ymin>
			<xmax>2024</xmax>
			<ymax>312</ymax>
		</bndbox>
	</object>
	<object>
		<name>negra</name>
		<pose>Unspecified</pose>
		<truncated>0</truncated>
		<difficult>0</difficult>
		<bndbox>
			<xmin>2261</xmin>
			<ymin>946</ymin>
			<xmax>2532</xmax>
			<ymax>1268</ymax>
		</bndbox>
	</object>
	<object>
		<name>negra</name>
		<pose>Unspecified</pose>
		<truncated>0</truncated>
		<difficult>0</difficult>
		<bndbox>
			<xmin>2065</xmin>
			<ymin>5</ymin>
			<xmax>2784</xmax>
			<ymax>353</ymax>
		</bndbox>
	</object>
</annotation>
