<annotation>
	<folder>wetransfer-6ed465</folder>
	<filename>IMG_8332.JPG</filename>
	<path>C:\Users\Guille\Documents\GitHub\images\Fulvia\wetransfer-6ed465\IMG_8332.JPG</path>
	<source>
		<database>Unknown</database>
	</source>
	<size>
		<width>3264</width>
		<height>2448</height>
		<depth>3</depth>
	</size>
	<segmented>0</segmented>
	<object>
		<name>negra</name>
		<pose>Unspecified</pose>
		<truncated>0</truncated>
		<difficult>0</difficult>
		<bndbox>
			<xmin>1821</xmin>
			<ymin>472</ymin>
			<xmax>2102</xmax>
			<ymax>735</ymax>
		</bndbox>
	</object>
	<object>
		<name>negra</name>
		<pose>Unspecified</pose>
		<truncated>0</truncated>
		<difficult>0</difficult>
		<bndbox>
			<xmin>1399</xmin>
			<ymin>1546</ymin>
			<xmax>1747</xmax>
			<ymax>1816</ymax>
		</bndbox>
	</object>
</annotation>
