<annotation>
	<folder>wetransfer-6ed465</folder>
	<filename>IMG_8246.JPG</filename>
	<path>C:\Users\Guille\Documents\GitHub\images\Fulvia\wetransfer-6ed465\IMG_8246.JPG</path>
	<source>
		<database>Unknown</database>
	</source>
	<size>
		<width>3264</width>
		<height>2448</height>
		<depth>3</depth>
	</size>
	<segmented>0</segmented>
	<object>
		<name>negra</name>
		<pose>Unspecified</pose>
		<truncated>0</truncated>
		<difficult>0</difficult>
		<bndbox>
			<xmin>284</xmin>
			<ymin>475</ymin>
			<xmax>1687</xmax>
			<ymax>1738</ymax>
		</bndbox>
	</object>
	<object>
		<name>negra</name>
		<pose>Unspecified</pose>
		<truncated>0</truncated>
		<difficult>0</difficult>
		<bndbox>
			<xmin>1591</xmin>
			<ymin>1583</ymin>
			<xmax>2461</xmax>
			<ymax>2205</ymax>
		</bndbox>
	</object>
	<object>
		<name>negra</name>
		<pose>Unspecified</pose>
		<truncated>0</truncated>
		<difficult>0</difficult>
		<bndbox>
			<xmin>1661</xmin>
			<ymin>875</ymin>
			<xmax>2750</xmax>
			<ymax>1527</ymax>
		</bndbox>
	</object>
	<object>
		<name>negra</name>
		<pose>Unspecified</pose>
		<truncated>0</truncated>
		<difficult>0</difficult>
		<bndbox>
			<xmin>2528</xmin>
			<ymin>2186</ymin>
			<xmax>2702</xmax>
			<ymax>2309</ymax>
		</bndbox>
	</object>
</annotation>
